mavis_config/__init__.py
mavis_config/config.json
mavis_config/constants.py
mavis_config/overlay.json
mavis_config-1.2.2.data/data/mavis_config/config.json
mavis_config-1.2.2.data/data/mavis_config/overlay.json
mavis_config-1.2.2.dist-info/LICENSE
mavis_config-1.2.2.dist-info/METADATA
mavis_config-1.2.2.dist-info/WHEEL
mavis_config-1.2.2.dist-info/top_level.txt
mavis_config-1.2.2.dist-info/RECORD
